oslo_vmware/__init__.py
oslo_vmware/_i18n.py
oslo_vmware/api.py
oslo_vmware/constants.py
oslo_vmware/dvs_util.py
oslo_vmware/exceptions.py
oslo_vmware/image_transfer.py
oslo_vmware/image_util.py
oslo_vmware/pbm.py
oslo_vmware/rw_handles.py
oslo_vmware/service.py
oslo_vmware/version.py
oslo_vmware/vim.py
oslo_vmware/vim_util.py
oslo_vmware/common/__init__.py
oslo_vmware/common/loopingcall.py
oslo_vmware/hacking/__init__.py
oslo_vmware/hacking/checks.py
oslo_vmware/locale/en_GB/LC_MESSAGES/oslo_vmware.po
oslo_vmware/locale/fr/LC_MESSAGES/oslo_vmware.po
oslo_vmware/objects/__init__.py
oslo_vmware/objects/datacenter.py
oslo_vmware/objects/datastore.py
oslo_vmware/tests/__init__.py
oslo_vmware/tests/base.py
oslo_vmware/tests/test.ovf
oslo_vmware/tests/test_api.py
oslo_vmware/tests/test_dvs_util.py
oslo_vmware/tests/test_exceptions.py
oslo_vmware/tests/test_hacking.py
oslo_vmware/tests/test_image_transfer.py
oslo_vmware/tests/test_image_util.py
oslo_vmware/tests/test_pbm.py
oslo_vmware/tests/test_rw_handles.py
oslo_vmware/tests/test_service.py
oslo_vmware/tests/test_vim.py
oslo_vmware/tests/test_vim_util.py
oslo_vmware/tests/objects/__init__.py
oslo_vmware/tests/objects/test_datacenter.py
oslo_vmware/tests/objects/test_datastore.py
oslo_vmware/wsdl/5.5/core-types.xsd
oslo_vmware/wsdl/5.5/pbm-messagetypes.xsd
oslo_vmware/wsdl/5.5/pbm-types.xsd
oslo_vmware/wsdl/5.5/pbm.wsdl
oslo_vmware/wsdl/5.5/pbmService.wsdl
oslo_vmware/wsdl/6.0/core-types.xsd
oslo_vmware/wsdl/6.0/pbm-messagetypes.xsd
oslo_vmware/wsdl/6.0/pbm-types.xsd
oslo_vmware/wsdl/6.0/pbm.wsdl
oslo_vmware/wsdl/6.0/pbmService.wsdl
oslo_vmware/wsdl/6.5/core-types.xsd
oslo_vmware/wsdl/6.5/pbm-messagetypes.xsd
oslo_vmware/wsdl/6.5/pbm-types.xsd
oslo_vmware/wsdl/6.5/pbm.wsdl
oslo_vmware/wsdl/6.5/pbmService.wsdl
oslo_vmware/wsdl/6.5/query-types.xsd
oslo_vmware/wsdl/6.5/reflect-types.xsd
oslo_vmware/wsdl/6.5/vim-types.xsd
oslo_vmware/wsdl/6.7/core-types.xsd
oslo_vmware/wsdl/6.7/pbm-messagetypes.xsd
oslo_vmware-4.8.0.dist-info/licenses/AUTHORS
oslo_vmware-4.8.0.dist-info/licenses/LICENSE
oslo_vmware-4.8.0.dist-info/METADATA
oslo_vmware-4.8.0.dist-info/WHEEL
oslo_vmware-4.8.0.dist-info/pbr.json
oslo_vmware-4.8.0.dist-info/top_level.txt
oslo_vmware-4.8.0.dist-info/RECORD
